list_session_inhibitors/__init__.py
list_session_inhibitors/inhibitors.py
list_session_inhibitors-0.9.8.dist-info/METADATA
list_session_inhibitors-0.9.8.dist-info/WHEEL
list_session_inhibitors-0.9.8.dist-info/entry_points.txt
list_session_inhibitors-0.9.8.dist-info/top_level.txt
list_session_inhibitors-0.9.8.dist-info/RECORD
