Metadata-Version: 2.1
Name: list-session-inhibitors
Version: 0.9.8
Summary: command line utility to list session power inhibitors for Linux Gnome desktop users
Home-page: https://github.com/timrichardson/gnome_inhibit_list
Author: Tim Richardson
Author-email: tim@growthpath.com.au
License: LGPLv3
Keywords: inhibitors
Platform: UNKNOWN
Classifier: Development Status :: 4 - Beta
Classifier: License :: OSI Approved :: GNU Lesser General Public License v3 (LGPLv3)
Classifier: Programming Language :: Python :: 3.6
Classifier: Programming Language :: Python :: 3.7
Classifier: Programming Language :: Python :: 3.8
Classifier: Programming Language :: Python :: 3.9
Classifier: Topic :: Office/Business
Requires-Python: >=3.6
Requires-Dist: pydbus
Requires-Dist: PyGObject (>=3.40)
Requires-Dist: click
